NLP_NLTK/__init__.py
NLP_NLTK/main.py
NLP_NLTK/practical1.py
NLP_NLTK/practical2.py
NLP_NLTK/practical4.py
NLP_NLTK-0.3.5.dist-info/LICENCE
NLP_NLTK-0.3.5.dist-info/METADATA
NLP_NLTK-0.3.5.dist-info/WHEEL
NLP_NLTK-0.3.5.dist-info/top_level.txt
NLP_NLTK-0.3.5.dist-info/RECORD
